gopnik/__init__.py
gopnik/_version.py
gopnik/cli.py
gopnik/ai/__init__.py
gopnik/ai/cv_engine.py
gopnik/ai/hybrid_engine.py
gopnik/ai/nlp_engine.py
gopnik/config/__init__.py
gopnik/config/config.py
gopnik/config/settings.py
gopnik/core/__init__.py
gopnik/core/analyzer.py
gopnik/core/interfaces.py
gopnik/core/processor.py
gopnik/core/redaction.py
gopnik/interfaces/__init__.py
gopnik/interfaces/api/__init__.py
gopnik/interfaces/api/app.py
gopnik/interfaces/api/cli.py
gopnik/interfaces/api/dependencies.py
gopnik/interfaces/api/job_manager.py
gopnik/interfaces/api/models.py
gopnik/interfaces/api/routers/__init__.py
gopnik/interfaces/api/routers/health.py
gopnik/interfaces/api/routers/processing.py
gopnik/interfaces/api/routers/profiles.py
gopnik/interfaces/api/routers/validation.py
gopnik/interfaces/cli/__init__.py
gopnik/interfaces/cli/base_command.py
gopnik/interfaces/cli/errors.py
gopnik/interfaces/cli/main.py
gopnik/interfaces/cli/progress.py
gopnik/interfaces/cli/commands/__init__.py
gopnik/interfaces/cli/commands/batch_command.py
gopnik/interfaces/cli/commands/process_command.py
gopnik/interfaces/cli/commands/profile_command.py
gopnik/interfaces/cli/commands/validate_command.py
gopnik/interfaces/web/__init__.py
gopnik/interfaces/web/endpoints.py
gopnik/interfaces/web/processing.py
gopnik/interfaces/web/routes.py
gopnik/interfaces/web/security.py
gopnik/interfaces/web/static/css/demo.css
gopnik/interfaces/web/static/css/welcome.css
gopnik/interfaces/web/static/js/demo.js
gopnik/interfaces/web/static/js/welcome.js
gopnik/interfaces/web/templates/demo.html
gopnik/interfaces/web/templates/welcome.html
gopnik/models/__init__.py
gopnik/models/audit.py
gopnik/models/errors.py
gopnik/models/pii.py
gopnik/models/processing.py
gopnik/models/profiles.py
gopnik/utils/__init__.py
gopnik/utils/audit_logger.py
gopnik/utils/crypto.py
gopnik/utils/file_utils.py
gopnik/utils/integrity_validator.py
gopnik/utils/logging_utils.py
gopnik/utils/memory_protection.py
gopnik-0.1.0.dist-info/licenses/LICENSE
gopnik-0.1.0.dist-info/METADATA
gopnik-0.1.0.dist-info/WHEEL
gopnik-0.1.0.dist-info/entry_points.txt
gopnik-0.1.0.dist-info/top_level.txt
gopnik-0.1.0.dist-info/RECORD
