Metadata-Version: 2.4
Name: gopnik
Version: 0.1.0
Summary: AI-powered forensic-grade deidentification toolkit
Home-page: https://github.com/happy2234/gopnik
Download-URL: https://github.com/happy2234/gopnik/archive/refs/tags/v0.1.0.tar.gz
Author: Gopnik Development Team
Author-email: Gopnik Development Team <dev@gopnik.ai>
Maintainer-email: Gopnik Development Team <dev@gopnik.ai>
License: MIT
Project-URL: Homepage, https://github.com/happy2234/gopnik
Project-URL: Documentation, https://happy2234.github.io/gopnik/
Project-URL: Repository, https://github.com/happy2234/gopnik
Project-URL: Bug Reports, https://github.com/happy2234/gopnik/issues
Project-URL: Changelog, https://github.com/happy2234/gopnik/releases
Project-URL: Wiki, https://github.com/happy2234/gopnik/wiki
Keywords: pii,deidentification,redaction,privacy,ai,forensic
Classifier: Development Status :: 3 - Alpha
Classifier: Intended Audience :: Developers
Classifier: Intended Audience :: Legal Industry
Classifier: Intended Audience :: Healthcare Industry
Classifier: License :: OSI Approved :: MIT License
Classifier: Operating System :: OS Independent
Classifier: Programming Language :: Python :: 3
Classifier: Programming Language :: Python :: 3.8
Classifier: Programming Language :: Python :: 3.9
Classifier: Programming Language :: Python :: 3.10
Classifier: Programming Language :: Python :: 3.11
Classifier: Programming Language :: Python :: 3.12
Classifier: Topic :: Security
Classifier: Topic :: Scientific/Engineering :: Artificial Intelligence
Classifier: Topic :: Text Processing
Classifier: Topic :: Office/Business
Classifier: Topic :: Software Development :: Libraries :: Python Modules
Requires-Python: >=3.8
License-File: LICENSE
Requires-Dist: pyyaml>=6.0
Requires-Dist: pydantic>=2.0
Requires-Dist: click>=8.0
Requires-Dist: cryptography>=3.4.8
Requires-Dist: pillow>=9.0.0
Requires-Dist: colorama>=0.4.4
Requires-Dist: tqdm>=4.64.0
Requires-Dist: pymupdf>=1.23.0
Provides-Extra: web
Requires-Dist: fastapi>=0.100.0; extra == "web"
Requires-Dist: uvicorn>=0.20.0; extra == "web"
Requires-Dist: python-multipart>=0.0.6; extra == "web"
Requires-Dist: jinja2>=3.1.0; extra == "web"
Requires-Dist: httpx>=0.24.0; extra == "web"
Provides-Extra: ai
Requires-Dist: torch>=2.0.0; extra == "ai"
Requires-Dist: torchvision>=0.15.0; extra == "ai"
Requires-Dist: transformers>=4.30.0; extra == "ai"
Requires-Dist: opencv-python>=4.8.0; extra == "ai"
Requires-Dist: numpy>=1.24.0; extra == "ai"
Requires-Dist: pymupdf>=1.23.0; extra == "ai"
Provides-Extra: dev
Requires-Dist: pytest>=7.0.0; extra == "dev"
Requires-Dist: pytest-cov>=4.0.0; extra == "dev"
Requires-Dist: pytest-asyncio>=0.21.0; extra == "dev"
Requires-Dist: httpx>=0.24.0; extra == "dev"
Requires-Dist: black>=23.0.0; extra == "dev"
Requires-Dist: flake8>=6.0.0; extra == "dev"
Requires-Dist: mypy>=1.0.0; extra == "dev"
Requires-Dist: build>=0.10.0; extra == "dev"
Requires-Dist: twine>=4.0.0; extra == "dev"
Provides-Extra: all
Requires-Dist: fastapi>=0.100.0; extra == "all"
Requires-Dist: uvicorn>=0.20.0; extra == "all"
Requires-Dist: python-multipart>=0.0.6; extra == "all"
Requires-Dist: jinja2>=3.1.0; extra == "all"
Requires-Dist: httpx>=0.24.0; extra == "all"
Requires-Dist: torch>=2.0.0; extra == "all"
Requires-Dist: torchvision>=0.15.0; extra == "all"
Requires-Dist: transformers>=4.30.0; extra == "all"
Requires-Dist: opencv-python>=4.8.0; extra == "all"
Requires-Dist: numpy>=1.24.0; extra == "all"
Requires-Dist: pymupdf>=1.23.0; extra == "all"
Requires-Dist: pytest>=7.0.0; extra == "all"
Requires-Dist: pytest-cov>=4.0.0; extra == "all"
Requires-Dist: pytest-asyncio>=0.21.0; extra == "all"
Dynamic: author
Dynamic: download-url
Dynamic: home-page
Dynamic: license-file
Dynamic: requires-python
